composio_claude/__init__.py
composio_claude/toolset.py
composio_claude-0.7.20.dist-info/METADATA
composio_claude-0.7.20.dist-info/WHEEL
composio_claude-0.7.20.dist-info/top_level.txt
composio_claude-0.7.20.dist-info/RECORD
