Metadata-Version: 2.4
Name: composio_claude
Version: 0.7.20
Summary: Use Composio to get an array of tools with your Claude LLMs.
Home-page: https://github.com/ComposioHQ/composio
Author: Sawradip
Author-email: sawradip@composio.dev
Classifier: Programming Language :: Python :: 3
Classifier: License :: OSI Approved :: Apache Software License
Classifier: Operating System :: OS Independent
Requires-Python: >=3.9,<4
Requires-Dist: composio_openai<0.8.0,>=0.5.0
Requires-Dist: anthropic>=0.25.7
Dynamic: author
Dynamic: author-email
Dynamic: classifier
Dynamic: description
Dynamic: description-content-type
Dynamic: home-page
Dynamic: requires-dist
Dynamic: requires-python
Dynamic: summary
